{"id": "m54-p0290", "collection": "murasoli", "volume": 54, "page": 290, "pageType": "body", "title": {"en": "Page 290", "ta": "பக்கம் 290"}, "paragraphs": ["தலைவர் கலைஞர் 289", "இந்தப் பிரச்சினையை சட்டப்படி முறையாக அணுகவில்லை என்று\nதெரிகிறது.", "2-12-2015 அன்று உச்ச நீதிமன்றத்தின் அரசியல் சாசன\nஅமர்வு அளித்த தீர்ப்பில், மத்தியப் புலனாய்வுத் துறை தொடுதத\nவழக்கில், ஆயுள் சிறை தண்டனை அனுபவித்து வரும் ராஜீவ்\nகாந்தி கொலைக் கைதிகள் ஏழு பேரையும் விடுதலை செய்வது\nதொடர்பாக முடிவெடுப்பதற்கான முதன்மையும் அதிகாரமும்\nமத்திய அரசுக்கே உண்டு என்று தெரிவித்திருக்கிறது.", "உச்ச நீதிமன்றம் அளித்துள்ள தீர்ப்பு, சட்டச் சிக்கல்\nமீதான விளக்கம் தானே தவிர, பேரறிவாளன், சாந்தன்,\nமுருகன் உள்ளிட்டோரின் விடுதலையை முற்றிலுமாகத\nதடுக்கக்கூடிய அம்சம் எதுவும், அந்தத் தீர்ப்பில் இல்லை என்று\nதான் வழக்கறிஞர்கள் கூறுகிறார்கள். சி.பி.ஐ. போன்ற மத்திய\nஅரசின் புலனாய்வு அமைப்புகளால் தாக்கல் செய்யப்பட்ட\nவழக்கில் தண்டனை பெற்ற கைதிகளை விடுதலை செய்யும்\nஅதிகாரம், சி.பி.ஐ. அமைப்பைத் தன்னுடைய அதிகாரத்தின்\nகீழே வைத்திருக்கின்ற மத்திய அரசுக்குத்தான் உள்ளது எனறும்,\nஅதன்படி தொடர்புடைய அரசு முடிவு செய்ய வேண்டுமென்கிற\nபோது, குறிப்பிட்ட இந்த வழக்கில் மத்திய அரசுக்குத்தான்\nஅதிகாரம் உள்ளது என்பதும்தான் உச்ச நீதிமன்றத் தீர்ப்பின்\nபொருளாகும். அதாவது மத்திய அரசின் அனுமதியுடன்\nவிடுவிக்கப்பட வேண்டும் என்பதுதான் இதன் மையநோக்கம்.", "ராஜீவ் காந்தி கொலை வழக்கில் தூக்குத் தண்டனை\nவிதிக்கப்பட்ட முருகன், சாந்தன், பேரறிவாளன் ஆகியோரின்\nகருணை மனுக்கள் மீது குடியரசுத் தலைவர் மிகவும் தாமதமாக\nமுடிவெடுத்ததாகக் கூறி, அவர்களின் தண்டனையை ஆயுள்\nசிறையாக உச்சநீதிமன்றம்தான் குறைத்தது. உச்சநீதிமன்றமே\nகூறிய காரணத்தால், 7 பேரையும் விடுதலை செய்ய தமிழகச்\nசட்டப்பேரவையில் மாநில அரசு 2014 ஆம் ஆண்டு பெப்ரவரியில்\nதீர்மானம் நிறைவேற்றியது. தீர்மானம் நிறைவேற்றியதும், குற்றஞு\nசாட்டப்பட்டவர்களை தமிழக அரசு விடுதலை செய்வதாகக்\nகூறியதும் தவறு அல்ல. அப்படிச் செய்த போது மத்திய அரசுக்குக்\nகட்டளையிடும் பாணியில், குறிப்பிட்ட நாட்களுக்குள் அதற்கு\nஒப்புதல் தர வேண்டும் என்று, அப்போது நிபந்தனை விதிப்பதைப்\nபோல ஜெயலலிதா அரசு நடந்து கொண்டிருக்கத் தேவையிலலை."], "ocrStatus": "ok"}