{"id": "m54-p0299", "collection": "murasoli", "volume": 54, "page": 299, "pageType": "body", "title": {"en": "Page 299", "ta": "பக்கம் 299"}, "paragraphs": ["298 கலைஞரின் கடிதங்கள்", "1991இல் பெரியார் விருது டாக்டர் சத்திய வாணிழுத்து -\nஅண்ணா விருதுதிரு. மீ.சு. இளமுருகு பொற்செல்வி - கலைஞர்\nவிருது திரு. நன்னிலம் நடராசன் ஆகியோருக்கும்; 1992இல்\nபெரியார் விருது திரு. நெல்லை ஆ. திராவிடமணி - அண்ணா", "சென்னிமலை லட்சுமியம்மாள் ஆகியோருக்கும்; 1995இல்\nபெரியார் விருது பத்தமடை ந. பரமசிவம் - அண்ணா விருது\nபுதுக்கோட்டை அ. பெரியண்ணன் - கலைஞர் விருது திண்டுக்கல்\nஎம்.ஏ. நூர்ஜகான் பேகம் ஆகியோருக்கும்; 1996இல் பெரியார்\nவிருது விருத்தாசலம் எம். செல்வராசன் - அண்ணாவிருது\nசொ. காவேரிமணியம் - கலைஞர் விருது போலீஸ் வெ. கண்ணன்\nஆகியோருக்கும்; 1997 இல் பெரியார் விருது பேராசிரியர் மா.\nநன்னன் - அண்ணா விருது பெங்களூர் கி. சோழன் - கலைஞர்", "விருது புலவர் ஆடலரசு ஆகியோருக்கும்;\n1998இல் பெரியார் விருது பூவாலூர் பி. சின்னத்துரை", "காஞ்சனா கமலநாதன் - பாவேந்தர் பாரதிதாசன் விருது பாவலா\nஇறையரசன் - கலைஞர் விருது கயல் தினகரன் ஆகியோருக்கும்;", "2002இல் பெரியார் விருது கரூர் வை. இரத்தின வேலு\n- அண்ணா விருது பெங்களூர் மா. மன்னர் - பாவேந்தர்\nபாரதிதாசன் விருது தஞ்சை கூத்தரசன் - கலைஞர் விருது கோவை\nமு. இராசம்மாள் ஆகியோருக்கும்; 2003இல் பெரியா விருது"], "ocrStatus": "ok"}