{"id": "m54-p0020", "collection": "murasoli", "volume": 54, "page": 20, "pageType": "body", "title": {"en": "Letter · 10-8-2016", "ta": "கடிதம் · 10-8-2016"}, "paragraphs": ["4037. என் முதல் பிள்ளை\n“முரசொலி“க்கு 10-8-2016 |211\nஇது பவள விழா ஆண்டு!", "4038. etn _சியில மகளி\nகா! சே 12-8-2016 | 219\nஇடஒதுக்கீடு?", "4039. 110வது விதியின்கீழ்\nஅறிக்கையும், அதற்கு 17822016 | 227\nவிளக்கமும்!", "4040. விவசாயிகளுக்கு\nஜெயலலிதாவின் அறிவிப்பு 20-8-2016 | 236\nவெறும் கண் துடைப்பு!", "4041. தமிழகச் சட்டமன்றத்தில்", "ஜனநாயகம் படும் பாடு!", "4042. அ.தி.மு.க. ஆட்சியில்", "சட்டம் ஒழுங்கு இலட்சணம்!", "4043. நிலைகுலைந்த ஆட்சி - நிரந்தர\nவீழ்ச்சி! ஜெயா தலைமையில் 2-9-2016 | 266\n100 நாள் வேதனைகள்!", "4044. தலைமைக் கணக்காயா\nபட்டியலிடும் தவறுகள் - 10-9-2016 | 275\nஇழப்புகள்!", "4045. வெண்ணெய் கையிலே", "இருக்கும்போது நெய்க்கு 15-09-2016 | 287\nஅலைவதா?", "4046. சூளுரை மேற்கொள்ள", "முப்பெரும் விழா", "16-9-2016 |294", "துணையரியட்டும்!"], "ocrStatus": "ok"}