{"id": "m54-p0171", "collection": "murasoli", "volume": 54, "page": 171, "pageType": "body", "title": {"en": "Page 171", "ta": "பக்கம் 171"}, "paragraphs": ["1 6டு கலைஞரின் கடிதங்கள்", "தமிழக அரசு செயல்பட்டு வருகிறது. மக்கள் நலனில் தமிழக\nமுதலமைச்சர் ஜெயலலிதாவுக்கு அக்கறை இல்லை. தமிழக மின்\nவாரியத்திற்குக் கடந்த ஆண்டுகளில் மட்டும் 12 ஆயிரம் கோடி\nரூபாய் அளவுக்கு இழப்பு ஏற்பட்டுள்ளது. மின் திருட்டு அதிகரித்து\nவருகிறது. அப்படியிருந்தும் தமிழகத்தில் மினசாரத துறையை\nநட்டத்திலிருந்து மீட்கவும், வருவாயை அதிகரிக்கவும் உதவும்\nமத்திய அரசின் “உதய்” என்னும் திட்டத்தைச் செயல்படுத்த\nமாநில அரசு முன்வரவில்லை. இத்திட்டத்தைப் பின்பற்றும் மற்ற\nமாநிலங்கள் நல்ல பலனைப் பெற்றுள்ளன; மற்ற மாநிலங்களில்\nசெயல்படுத்தியதன் மூலம் 1.80 லட்சம் கோடி ரூபாய் அளவுக்குப்\nபலன் கிடைத்துள்ளது. ஆனால் தமிழக அரசுக்கு மக்கள் நலனில்\nஅக்கறை இல்லாததால், மின் நுகர்வோர் பயன்பெறுவதைத் தமிழக\nஅரசு விரும்பவில்லை” என்று தமிழக அரசையும் முதலமைச்சர்\nஜெயலலிதாவையும் நேரடியாகவே குற்றம் சாட்டியிருந்தார்.", "ஜெயலலிதாவும், அமைச்சர்களும் முறையே தேர்தல்\nபிரச்சாரத்திலும், அறிக்கை மூலமாகவும் “உதய” திட்டம்\nபற்றி எழுப்பியிருக்கும் பிரச்சினைகளுக்குத் தற்போது\nமாநில நலனுக்கு உகந்த உரிய தீர்வு காணப்பட்டுவிட்டதா?", "தனியார் மின் உற்பத்தியாளாகளுக்கும,\nவங்கிகளுக்கும் இலாபகரமாக அமைந்திருக்கும் இந்தத்\nதிட்டத்தினால் தமிழக அரசுக்கும், தமிழக மக்களுக்கும்\nபாதிப்பே ஏற்படும் என்று சொன்னீர்களே; தற்போது அந்த\nபாதிப்பு நீக்கப்பட்டுவிட்டதா?", "அடுத்த ஆண்டிலிருந்து மாநில அரசால் கடன்\nஎதையும் பெற இயலாது என்று சொன்னாகளே; தற்போது\nமாநில அரசு கடன் பெறக் கூடிய நிலைமை உருவாக்கப்\nபட்டிருக்கிறதா?", "வளர்ச்சித் திட்டங்கள் எதையும் செயல்படுத்த\nஇயலாது என்று சொன்ன்களே; வளர்ச்சித் திட்டங்களைச்\nசெயல்படுத்துவதற்கு உகந்த நிலை தற்போது\nஏற்படுத்தப்பட்டிருக்கிறதா?"], "ocrStatus": "ok"}