{"id": "m54-p0156", "collection": "murasoli", "volume": 54, "page": 156, "pageType": "body", "title": {"en": "Page 156", "ta": "பக்கம் 156"}, "paragraphs": ["தலைவர் கலைஞர் 155", "சென்னையில் “மெட்ரோ ரெயில்” சோதனை ஓட்டத்தை\nமுதல் அமைச்சர் ஜெயலலிதா தொடங்கிவைத்தார். 14,600\nகோடி ரூபாய்க்கான திட்டம் அது. அந்தத் திட்டத்தைத் தொடங்கி ©\nவைத்த முதலமைச்சர் ஒரு வார்த்தைகூடப் பேசவில்லை.\nஅன்றாடம் தலைமைச் செயலகத்திலிருந்து “ காணொலிக்\nகாட்சிகள்” மூலமாகப் பல திட்டங்களைத் தொடங்கிவைப்பதைப்\nபோல இலலாமல், இந்தத் திட்டத்திற்கு நேரிலே வந்து\nதொடங்கிவைத்தாா. அந்தத் திட்டத்தைப் பற்றி அதனைத்\nதொடங்கிவைக்கும் விழாவிலே பேசிட வேண்டுமென்றால்,\nஅந்தத் திட்டம் எந்த ஆட்சியில், எந்த ஆண்டு தொடங்கப்பட்டது\nஎனபதைப் பற்றியெலலாம் கூற வேண்டுமல்லவா? அதனால்\nஅங்கே விழாப் பேருரை எதுவும் இல்லாமல் கொடி அசைத்து,\nமெட்ரோ ரெயிலின் சோதனையோட்டத்தைத் தொடங்கிவைத்து\nவிட்டார். அவர் அங்கே உரையாற்றாவிட்டாலும், அந்தத்\nதிட்டத்தைப் பற்றிய குறிப்பு தமிழக அரசினால் தரப்பட்டது.\nஅதிலே அந்தத் திட்டத்தைப் பற்றிய குறிப்புகள் விவரிக்கப்பட்ட\nபோதிலும், கவனமாக அது எந்த ஆட்சிக் காலத்தில்\nதொடங்கப்பட்டது என்பதை விட்டு விட்டார்கள். அந்தத் திட்டம்\nதிராவிட முன்னேற்றக் கழக ஆட்சியில், நான் முதலமைச்சராக\nஇருந்தபோது தொடங்கப்பட்ட திட்டம்.", "சென்னையில் “மெட்ரோ ரெயில்” திட்டத்தைச் செயல்படுத்த\nதி.மு. கழகம் 2006ஆம் ஆண்டு எனது தலைமையில் ஆட்சிப்\nபொறுப்புக்கு வந்தவுடன் தமிழக அமைச்சரவையில் அப்போதுதான்\nமுடிவெடுக்கப்பட்டது. விரைவான, நம்பத்தக்க, வசதியான,\nதிறன்மிக்க, நவீன மற்றும் சிக்கனமான பொதுப்போக்குவரத்து\nஅமைப்பாகவும், பெருகிவரும் போக்குவரத்துத் தேவைகளுக்கு\nஒரு நீண்டகாலத் தீர்வாகவும் அமைந்த இத்திட்டம் குறித்து,\nஒரு விரிவான திட்ட அறிக்கையினைத் தயாரிக்கக் கழக அரசு\nஆணையிட்டதைத் தொடர்ந்து, இந்தப் பணி டெல்லி மெட்ரோ\nஇரயில் கழகத்திடம் அளிக்கப்பட்டது. இத்திட்டம் என்னுடைய\nநேரடிக் கட்டுப்பாட்டின்கீழ் “சிறப்பு முயற்சித்” திட்டமாக அறி\nவிக்கப்பட்டது. அதன் பின்னர் இத்திட்டம் துணை முதலமைச்சராக\nஇருந்த தம்பி ஸ்டாலின் பொறுப்பிற்கு மாற்றப்பட்டது. விரிவான\nதிட்ட அறிக்கை 1-11-2007இல் கிடைக்கப்பெற்று 7-11-2007"], "ocrStatus": "ok"}