{"id": "m54-p0158", "collection": "murasoli", "volume": 54, "page": 158, "pageType": "body", "title": {"en": "Page 158", "ta": "பக்கம் 158"}, "paragraphs": ["தலைவர் கலைஞர் HON", "தி.மு. கழக ஆட்சியிலேதான். மத்திய அரசு திட்டச் செலவில்\n15 சதவீதத்தை பங்குத் தொகையாகவும், 5 சதவீதத்தைக்\nகடனாகவும் வழங்கும். மாநில அரசின் பங்கு 15 சதவிகிதம் மற்றும்\n5.£8 சதவிகித சார்நிலைக் கடனாகவும் வழங்கும். பொருளாதார\nவிவகாரங்களுக்கான மத்திய அமைச்சரவைக் குழு, 28-1-2009\nஅன்று நடைபெற்ற கூட்டத்தில் சென்னை மெட்ரோ இரயில்\nதிட்டத்திற்கு ஒப்புதல் அளித்துள்ளது. அதுவும் தி.மு. கழக\nஆட்சியிலேதான். இந்த மெட்ரோ ரெயில் திட்டம் 45.1 கிலோ மீட்டர்\nதூரத்திற்கு 2 வழித் தடங்களில் அமைக்கப்பட்டு வருகின்றன.\nவண்ணாரப்பேட்டை - சென்னை விமான நிலையம் இடையே\n23.1 கிலோ மீட்டர் தூரத்திற்கு முதல் வழித்தடமும், சென்ட்ரல்\n- பரங்கிமலை இடையே 22 கிலோ மீட்டர் தொலைவிற்கு 2-வது\nவழித்தடமும் அமைக்கப்படுகிறது. மெட்ரோ ரெயிலானது 2 வழித்\nதடங்களிலும், செல்வதற்கு ஒன்றும், வருவதற்கு ஒன்றுமாக\nஇரண்டு பாதைகள் நவீன முறையில் அமைக்கப்படுகின்றன.\nஇதையெல்லாம் அப்படியே மூடி மறைத்துவிட்டு, அ.தி.மு.க.\nஆட்சியிலேதான் மெட்ரோ திட்டத்திற்கு வித்திடப்பட்டது", "என்றால் யார் அதனை நம்புவார்கள்?", "திராவிட முன்னேற்றக் கழக ஆட்சியில் இவ்வாறு\nமுனைப்போடு முயற்சித்துத் தொடங்கப்பட்ட திட்டம்தான்\n“மெட்ரோ ரயில்” திட்டம். ஆனால் ஜெயலலிதா ஆட்சிப்\nபொறுப்புக்கு வந்தவுடன் இதைப் பற்றி என்னவெல்லாம் பேசினார்\nதெரியுமா?", "2011 ஆம் ஆண்டில், ஆட்சிப் பொறுப்பேற்றவுடன், அ.தி.மு.க.\nஅரசு 3-6-2011 அன்று படித்த ஆளுநர் அறிக்கையிலேயே,\n“சென்னை மாநகருக்குத் தற்போதுள்ள போக்குவரத்து\nமுறைகளுடன் ஒருங்கிணைந்து செயல்பட மோனோ இரயில்\nதிட்டத்தை அரசு செயல்படுத்தும். முதற்கட்டமாக 111 கிலோ\nமீட்டருக்கு இத்திட்டம் செயல்படுத்தப்பட்டு, படிப்படியாக 300\nகிலோ மீட்டர் வரை விரிவுபடுத்தப்படும். கோயம்புத்தூர், மதுரை\nமற்றும் திருச்சி போன்ற மாநகராட்சிகளிலும் போக்கு வரத்து\nநெரிசலைக் குறைக்க “மோனோ ரெயில்” திட்டம் செயலபடுத்த\nஉரிய ஆய்வுகள் மேற்கொள்ளப்படும்” என்று அறிவித்தார்களே"], "ocrStatus": "ok"}